[
  {
    "live_tv_id": "2",
    "tv_name": "Divya TV",
    "description": "",
    "slug": "",
    "stream_from": "hls",
    "stream_label": "HD",
    "user_agent": "ExoPlayerDemo/16.27.14 (Linux;Android 6.0.1) ExoPlayerLib/2.8.4",
    "stream_url": "https://angelon.top/apis/livetv/zee5/play.m3u8?id=DIVYA_TV&token=ZnVja3lvdWJpdGNo",
    "thumbnail_url": "divyatv386x386_1472508996.png",
    "poster_url": "divyatv386x386_1472508996.png",
    "original_thumbnail_url": "https://akamaividz.zee5.com/resources/0-9-divyatv/list/339x339/divyatv386x386_1472508996.png",
    "original_poster_url": "https://akamaividz.zee5.com/resources/0-9-divyatv/list/339x339/divyatv386x386_1472508996.png"
  },
  {
    "live_tv_id": "3",
    "tv_name": "Sanskar TV",
    "description": "",
    "slug": "",
    "stream_from": "hls",
    "stream_label": "HD",
    "user_agent": "ExoPlayerDemo/16.27.14 (Linux;Android 6.0.1) ExoPlayerLib/2.8.4",
    "stream_url": "https://angelon.top/apis/livetv/zee5/play.m3u8?id=SANSKAR_TV&token=ZnVja3lvdWJpdGNo",
    "thumbnail_url": "sanskarlogo386x386.png",
    "poster_url": "sanskarlogo386x386.png",
    "original_thumbnail_url": "https://akamaividz.zee5.com/resources/0-9-channel_1144658965/list/339x339/sanskarlogo386x386.png",
    "original_poster_url": "https://akamaividz.zee5.com/resources/0-9-channel_1144658965/list/339x339/sanskarlogo386x386.png"
  },
  {
    "live_tv_id": "4",
    "tv_name": "Living Foodz",
    "description": "",
    "slug": "",
    "stream_from": "hls",
    "stream_label": "HD",
    "user_agent": "ExoPlayerDemo/16.27.14 (Linux;Android 6.0.1) ExoPlayerLib/2.8.4",
    "stream_url": "https://angelon.top/apis/livetv/zee5/play.m3u8?id=LIVING_FOODZ&token=ZnVja3lvdWJpdGNo",
    "thumbnail_url": "lf1170x658.png",
    "poster_url": "lf1170x658.png",
    "original_thumbnail_url": "https://akamaividz.zee5.com/resources/0-9-livingfoodz/list/339x339/lf1170x658.png",
    "original_poster_url": "https://akamaividz.zee5.com/resources/0-9-livingfoodz/list/339x339/lf1170x658.png"
  },
  {
    "live_tv_id": "5",
    "tv_name": "EZ Mall",
    "description": "",
    "slug": "",
    "stream_from": "hls",
    "stream_label": "HD",
    "user_agent": "ExoPlayerDemo/16.27.14 (Linux;Android 6.0.1) ExoPlayerLib/2.8.4",
    "stream_url": "https://angelon.top/apis/livetv/zee5/play.m3u8?id=EZ_MALL&token=ZnVja3lvdWJpdGNo",
    "thumbnail_url": "ezmall_386x386.png",
    "poster_url": "ezmall_386x386.png",
    "original_thumbnail_url": "https://akamaividz.zee5.com/resources/0-9-channel_477236247/list/339x339/ezmall_386x386.png",
    "original_poster_url": "https://akamaividz.zee5.com/resources/0-9-channel_477236247/list/339x339/ezmall_386x386.png"
  },
  {
    "live_tv_id": "6",
    "tv_name": "Zing",
    "description": "",
    "slug": "",
    "stream_from": "hls",
    "stream_label": "HD",
    "user_agent": "ExoPlayerDemo/16.27.14 (Linux;Android 6.0.1) ExoPlayerLib/2.8.4",
    "stream_url": "https://angelon.top/apis/livetv/zee5/play.m3u8?id=ZING&token=ZnVja3lvdWJpdGNo",
    "thumbnail_url": "zing_582493460.png",
    "poster_url": "zing_582493460.png",
    "original_thumbnail_url": "https://akamaividz.zee5.com/resources/0-9-zing/list/339x339/zing_582493460.png",
    "original_poster_url": "https://akamaividz.zee5.com/resources/0-9-zing/list/339x339/zing_582493460.png"
  },
  {
    "live_tv_id": "7",
    "tv_name": "DD Chandana",
    "description": "",
    "slug": "",
    "stream_from": "hls",
    "stream_label": "HD",
    "user_agent": "ExoPlayerDemo/16.27.14 (Linux;Android 6.0.1) ExoPlayerLib/2.8.4",
    "stream_url": "https://angelon.top/apis/livetv/zee5/play.m3u8?id=DD_CHANDANA&token=ZnVja3lvdWJpdGNo",
    "thumbnail_url": "ddchandana386x38_475457013.png",
    "poster_url": "ddchandana386x38_475457013.png",
    "original_thumbnail_url": "https://akamaividz.zee5.com/resources/0-9-ddchandana/list/339x339/ddchandana386x38_475457013.png",
    "original_poster_url": "https://akamaividz.zee5.com/resources/0-9-ddchandana/list/339x339/ddchandana386x38_475457013.png"
  },
  {
    "live_tv_id": "8",
    "tv_name": "Zee Kannada",
    "description": "",
    "slug": "",
    "stream_from": "hls",
    "stream_label": "HD",
    "user_agent": "ExoPlayerDemo/16.27.14 (Linux;Android 6.0.1) ExoPlayerLib/2.8.4",
    "stream_url": "https://angelon.top/apis/livetv/zee5/play.m3u8?id=ZEE_KANNADA&token=ZnVja3lvdWJpdGNo",
    "thumbnail_url": "h2logo386x386_129695504.png",
    "poster_url": "h2logo386x386_129695504.png",
    "original_thumbnail_url": "https://akamaividz.zee5.com/resources/0-9-zeekannada/list/339x339/h2logo386x386_129695504.png",
    "original_poster_url": "https://akamaividz.zee5.com/resources/0-9-zeekannada/list/339x339/h2logo386x386_129695504.png"
  },
  {
    "live_tv_id": "9",
    "tv_name": "Zee Cinemalu",
    "description": "",
    "slug": "",
    "stream_from": "hls",
    "stream_label": "HD",
    "user_agent": "ExoPlayerDemo/16.27.14 (Linux;Android 6.0.1) ExoPlayerLib/2.8.4",
    "stream_url": "https://angelon.top/apis/livetv/zee5/play.m3u8?id=ZEE_CINEMALU&token=ZnVja3lvdWJpdGNo",
    "thumbnail_url": "zeecinamalufinal.png",
    "poster_url": "zeecinamalufinal.png",
    "original_thumbnail_url": "https://akamaividz.zee5.com/resources/0-9-zeecinemalu/list/339x339/zeecinamalufinal.png",
    "original_poster_url": "https://akamaividz.zee5.com/resources/0-9-zeecinemalu/list/339x339/zeecinamalufinal.png"
  },
  {
    "live_tv_id": "10",
    "tv_name": "Zee Telugu",
    "description": "",
    "slug": "",
    "stream_from": "hls",
    "stream_label": "HD",
    "user_agent": "ExoPlayerDemo/16.27.14 (Linux;Android 6.0.1) ExoPlayerLib/2.8.4",
    "stream_url": "https://angelon.top/apis/livetv/zee5/play.m3u8?id=ZEE_TELUGU&token=ZnVja3lvdWJpdGNo",
    "thumbnail_url": "zeetelugu_383969457.png",
    "poster_url": "zeetelugu_383969457.png",
    "original_thumbnail_url": "https://akamaividz.zee5.com/resources/0-9-zeetelugu/list/339x339/zeetelugu_383969457.png",
    "original_poster_url": "https://akamaividz.zee5.com/resources/0-9-zeetelugu/list/339x339/zeetelugu_383969457.png"
  },
  {
    "live_tv_id": "11",
    "tv_name": "Zee Talkies",
    "description": "",
    "slug": "",
    "stream_from": "hls",
    "stream_label": "HD",
    "user_agent": "ExoPlayerDemo/16.27.14 (Linux;Android 6.0.1) ExoPlayerLib/2.8.4",
    "stream_url": "https://angelon.top/apis/livetv/zee5/play.m3u8?id=ZEE_TALKIES&token=ZnVja3lvdWJpdGNo",
    "thumbnail_url": "zeetalkies_293545487.png",
    "poster_url": "zeetalkies_293545487.png",
    "original_thumbnail_url": "https://akamaividz.zee5.com/resources/0-9-zeetalkies/list/339x339/zeetalkies_293545487.png",
    "original_poster_url": "https://akamaividz.zee5.com/resources/0-9-zeetalkies/list/339x339/zeetalkies_293545487.png"
  },
  {
    "live_tv_id": "12",
    "tv_name": "DD Sahyadri",
    "description": "",
    "slug": "",
    "stream_from": "hls",
    "stream_label": "HD",
    "user_agent": "ExoPlayerDemo/16.27.14 (Linux;Android 6.0.1) ExoPlayerLib/2.8.4",
    "stream_url": "https://angelon.top/apis/livetv/zee5/play.m3u8?id=DD_SAHYADRI&token=ZnVja3lvdWJpdGNo",
    "thumbnail_url": "dd_sahyadri386x3_186509040.png",
    "poster_url": "dd_sahyadri386x3_186509040.png",
    "original_thumbnail_url": "https://akamaividz.zee5.com/resources/0-9-ddsahyadri/list/339x339/dd_sahyadri386x3_186509040.png",
    "original_poster_url": "https://akamaividz.zee5.com/resources/0-9-ddsahyadri/list/339x339/dd_sahyadri386x3_186509040.png"
  },
  {
    "live_tv_id": "13",
    "tv_name": "Zee Yuva",
    "description": "",
    "slug": "",
    "stream_from": "hls",
    "stream_label": "HD",
    "user_agent": "ExoPlayerDemo/16.27.14 (Linux;Android 6.0.1) ExoPlayerLib/2.8.4",
    "stream_url": "https://angelon.top/apis/livetv/zee5/play.m3u8?id=ZEE_YUVA&token=ZnVja3lvdWJpdGNo",
    "thumbnail_url": "zeeyuva_1608077288.png",
    "poster_url": "zeeyuva_1608077288.png",
    "original_thumbnail_url": "https://akamaividz.zee5.com/resources/0-9-zeeyuva/list/339x339/zeeyuva_1608077288.png",
    "original_poster_url": "https://akamaividz.zee5.com/resources/0-9-zeeyuva/list/339x339/zeeyuva_1608077288.png"
  },
  {
    "live_tv_id": "14",
    "tv_name": "Zee Marathi HD",
    "description": "",
    "slug": "",
    "stream_from": "hls",
    "stream_label": "HD",
    "user_agent": "ExoPlayerDemo/16.27.14 (Linux;Android 6.0.1) ExoPlayerLib/2.8.4",
    "stream_url": "https://angelon.top/apis/livetv/zee5/play.m3u8?id=ZEE_MARATHI_HD&token=ZnVja3lvdWJpdGNo",
    "thumbnail_url": "1170x658_910988430.png",
    "poster_url": "1170x658_910988430.png",
    "original_thumbnail_url": "https://akamaividz.zee5.com/resources/0-9-zeemarathi/list/339x339/1170x658_910988430.png",
    "original_poster_url": "https://akamaividz.zee5.com/resources/0-9-zeemarathi/list/339x339/1170x658_910988430.png"
  },
  {
    "live_tv_id": "15",
    "tv_name": "Zee 24 Taas",
    "description": "",
    "slug": "",
    "stream_from": "hls",
    "stream_label": "HD",
    "user_agent": "ExoPlayerDemo/16.27.14 (Linux;Android 6.0.1) ExoPlayerLib/2.8.4",
    "stream_url": "https://angelon.top/apis/livetv/zee5/play.m3u8?id=ZEE_24_TAAS&token=ZnVja3lvdWJpdGNo",
    "thumbnail_url": "zee24tass.png",
    "poster_url": "zee24tass.png",
    "original_thumbnail_url": "https://akamaividz.zee5.com/resources/0-9-zee24taas/list/339x339/zee24tass.png",
    "original_poster_url": "https://akamaividz.zee5.com/resources/0-9-zee24taas/list/339x339/zee24tass.png"
  },
  {
    "live_tv_id": "16",
    "tv_name": "BloombergQuint",
    "description": "",
    "slug": "",
    "stream_from": "hls",
    "stream_label": "HD",
    "user_agent": "ExoPlayerDemo/16.27.14 (Linux;Android 6.0.1) ExoPlayerLib/2.8.4",
    "stream_url": "https://angelon.top/apis/livetv/zee5/play.m3u8?id=BLOOMBERGQUINT&token=ZnVja3lvdWJpdGNo",
    "thumbnail_url": "zee386x386bqhqc.png",
    "poster_url": "zee386x386bqhqc.png",
    "original_thumbnail_url": "https://akamaividz.zee5.com/resources/0-9-143/list/339x339/zee386x386bqhqc.png",
    "original_poster_url": "https://akamaividz.zee5.com/resources/0-9-143/list/339x339/zee386x386bqhqc.png"
  },
  {
    "live_tv_id": "17",
    "tv_name": "Republic TV",
    "description": "",
    "slug": "",
    "stream_from": "hls",
    "stream_label": "HD",
    "user_agent": "ExoPlayerDemo/16.27.14 (Linux;Android 6.0.1) ExoPlayerLib/2.8.4",
    "stream_url": "https://angelon.top/apis/livetv/zee5/play.m3u8?id=REPUBLIC_TV&token=ZnVja3lvdWJpdGNo",
    "thumbnail_url": "republic_tv_color.png",
    "poster_url": "republic_tv_color.png",
    "original_thumbnail_url": "https://akamaividz.zee5.com/resources/0-9-channel_1422341819/list/339x339/republic_tv_color.png",
    "original_poster_url": "https://akamaividz.zee5.com/resources/0-9-channel_1422341819/list/339x339/republic_tv_color.png"
  },
  {
    "live_tv_id": "18",
    "tv_name": "DD Kisan",
    "description": "",
    "slug": "",
    "stream_from": "hls",
    "stream_label": "HD",
    "user_agent": "ExoPlayerDemo/16.27.14 (Linux;Android 6.0.1) ExoPlayerLib/2.8.4",
    "stream_url": "https://angelon.top/apis/livetv/zee5/play.m3u8?id=DD_KISAN&token=ZnVja3lvdWJpdGNo",
    "thumbnail_url": "ddkisan_386x386.png",
    "poster_url": "ddkisan_386x386.png",
    "original_thumbnail_url": "https://akamaividz.zee5.com/resources/0-9-ddkisan/list/339x339/ddkisan_386x386.png",
    "original_poster_url": "https://akamaividz.zee5.com/resources/0-9-ddkisan/list/339x339/ddkisan_386x386.png"
  },
  {
    "live_tv_id": "19",
    "tv_name": "DD News",
    "description": "",
    "slug": "",
    "stream_from": "hls",
    "stream_label": "HD",
    "user_agent": "ExoPlayerDemo/16.27.14 (Linux;Android 6.0.1) ExoPlayerLib/2.8.4",
    "stream_url": "https://angelon.top/apis/livetv/zee5/play.m3u8?id=DD_NEWS&token=ZnVja3lvdWJpdGNo",
    "thumbnail_url": "ddnews_386x386.png",
    "poster_url": "ddnews_386x386.png",
    "original_thumbnail_url": "https://akamaividz.zee5.com/resources/0-9-ddnews/list/339x339/ddnews_386x386.png",
    "original_poster_url": "https://akamaividz.zee5.com/resources/0-9-ddnews/list/339x339/ddnews_386x386.png"
  },
  {
    "live_tv_id": "20",
    "tv_name": "DD India",
    "description": "",
    "slug": "",
    "stream_from": "hls",
    "stream_label": "HD",
    "user_agent": "ExoPlayerDemo/16.27.14 (Linux;Android 6.0.1) ExoPlayerLib/2.8.4",
    "stream_url": "https://angelon.top/apis/livetv/zee5/play.m3u8?id=DD_INDIA&token=ZnVja3lvdWJpdGNo",
    "thumbnail_url": "ddindia_386x386.png",
    "poster_url": "ddindia_386x386.png",
    "original_thumbnail_url": "https://akamaividz.zee5.com/resources/0-9-ddindia/list/339x339/ddindia_386x386.png",
    "original_poster_url": "https://akamaividz.zee5.com/resources/0-9-ddindia/list/339x339/ddindia_386x386.png"
  },
  {
    "live_tv_id": "22",
    "tv_name": "WION",
    "description": "",
    "slug": "",
    "stream_from": "hls",
    "stream_label": "HD",
    "user_agent": "ExoPlayerDemo/16.27.14 (Linux;Android 6.0.1) ExoPlayerLib/2.8.4",
    "stream_url": "https://angelon.top/apis/livetv/zee5/play.m3u8?id=WION&token=ZnVja3lvdWJpdGNo",
    "thumbnail_url": "wion386x386_1766817197.png",
    "poster_url": "wion386x386_1766817197.png",
    "original_thumbnail_url": "https://akamaividz.zee5.com/resources/0-9-wion/list/339x339/wion386x386_1766817197.png",
    "original_poster_url": "https://akamaividz.zee5.com/resources/0-9-wion/list/339x339/wion386x386_1766817197.png"
  },
  {
    "live_tv_id": "23",
    "tv_name": "Zee Hindustan",
    "description": "",
    "slug": "",
    "stream_from": "hls",
    "stream_label": "HD",
    "user_agent": "ExoPlayerDemo/16.27.14 (Linux;Android 6.0.1) ExoPlayerLib/2.8.4",
    "stream_url": "https://angelon.top/apis/livetv/zee5/play.m3u8?id=ZEE_HINDUSTAN&token=ZnVja3lvdWJpdGNo",
    "thumbnail_url": "zeehindustan.png",
    "poster_url": "zeehindustan.png",
    "original_thumbnail_url": "https://akamaividz.zee5.com/resources/0-9-zeehindustan/list/339x339/zeehindustan.png",
    "original_poster_url": "https://akamaividz.zee5.com/resources/0-9-zeehindustan/list/339x339/zeehindustan.png"
  },
  {
    "live_tv_id": "24",
    "tv_name": "News Nation",
    "description": "",
    "slug": "",
    "stream_from": "hls",
    "stream_label": "HD",
    "user_agent": "ExoPlayerDemo/16.27.14 (Linux;Android 6.0.1) ExoPlayerLib/2.8.4",
    "stream_url": "https://angelon.top/apis/livetv/zee5/play.m3u8?id=NEWS_NATION&token=ZnVja3lvdWJpdGNo",
    "thumbnail_url": "nn.png",
    "poster_url": "nn.png",
    "original_thumbnail_url": "https://akamaividz.zee5.com/resources/0-9-170/list/339x339/nn.png",
    "original_poster_url": "https://akamaividz.zee5.com/resources/0-9-170/list/339x339/nn.png"
  },
  {
    "live_tv_id": "25",
    "tv_name": "BloombergQuint",
    "description": "",
    "slug": "",
    "stream_from": "hls",
    "stream_label": "HD",
    "user_agent": "ExoPlayerDemo/16.27.14 (Linux;Android 6.0.1) ExoPlayerLib/2.8.4",
    "stream_url": "https://angelon.top/apis/livetv/zee5/play.m3u8?id=BLOOMBERGQUINT&token=ZnVja3lvdWJpdGNo",
    "thumbnail_url": "zee386x386bqhqc.png",
    "poster_url": "zee386x386bqhqc.png",
    "original_thumbnail_url": "https://akamaividz.zee5.com/resources/0-9-143/list/339x339/zee386x386bqhqc.png",
    "original_poster_url": "https://akamaividz.zee5.com/resources/0-9-143/list/339x339/zee386x386bqhqc.png"
  },
  {
    "live_tv_id": "26",
    "tv_name": "Zee Business",
    "description": "",
    "slug": "",
    "stream_from": "hls",
    "stream_label": "HD",
    "user_agent": "ExoPlayerDemo/16.27.14 (Linux;Android 6.0.1) ExoPlayerLib/2.8.4",
    "stream_url": "https://angelon.top/apis/livetv/zee5/play.m3u8?id=ZEE_BUSINESS&token=ZnVja3lvdWJpdGNo",
    "thumbnail_url": "zeebusiness_1320695672.png",
    "poster_url": "zeebusiness_1320695672.png",
    "original_thumbnail_url": "https://akamaividz.zee5.com/resources/0-9-zeebusiness/list/339x339/zeebusiness_1320695672.png",
    "original_poster_url": "https://akamaividz.zee5.com/resources/0-9-zeebusiness/list/339x339/zeebusiness_1320695672.png"
  },
  {
    "live_tv_id": "27",
    "tv_name": "Republic TV",
    "description": "",
    "slug": "",
    "stream_from": "hls",
    "stream_label": "HD",
    "user_agent": "ExoPlayerDemo/16.27.14 (Linux;Android 6.0.1) ExoPlayerLib/2.8.4",
    "stream_url": "https://angelon.top/apis/livetv/zee5/play.m3u8?id=REPUBLIC_TV&token=ZnVja3lvdWJpdGNo",
    "thumbnail_url": "republic_tv_color.png",
    "poster_url": "republic_tv_color.png",
    "original_thumbnail_url": "https://akamaividz.zee5.com/resources/0-9-channel_1422341819/list/339x339/republic_tv_color.png",
    "original_poster_url": "https://akamaividz.zee5.com/resources/0-9-channel_1422341819/list/339x339/republic_tv_color.png"
  },
  {
    "live_tv_id": "28",
    "tv_name": "Zee 24 Taas",
    "description": "",
    "slug": "",
    "stream_from": "hls",
    "stream_label": "HD",
    "user_agent": "ExoPlayerDemo/16.27.14 (Linux;Android 6.0.1) ExoPlayerLib/2.8.4",
    "stream_url": "https://angelon.top/apis/livetv/zee5/play.m3u8?id=ZEE_24_TAAS&token=ZnVja3lvdWJpdGNo",
    "thumbnail_url": "zee24tass.png",
    "poster_url": "zee24tass.png",
    "original_thumbnail_url": "https://akamaividz.zee5.com/resources/0-9-zee24taas/list/339x339/zee24tass.png",
    "original_poster_url": "https://akamaividz.zee5.com/resources/0-9-zee24taas/list/339x339/zee24tass.png"
  },
  {
    "live_tv_id": "29",
    "tv_name": "Republic Bharat",
    "description": "",
    "slug": "",
    "stream_from": "hls",
    "stream_label": "HD",
    "user_agent": "ExoPlayerDemo/16.27.14 (Linux;Android 6.0.1) ExoPlayerLib/2.8.4",
    "stream_url": "https://angelon.top/apis/livetv/zee5/play.m3u8?id=REPUBLIC_BHARAT&token=ZnVja3lvdWJpdGNo",
    "thumbnail_url": "rbharat386x386_996253913.png",
    "poster_url": "rbharat386x386_996253913.png",
    "original_thumbnail_url": "https://akamaividz.zee5.com/resources/0-9-162/list/339x339/rbharat386x386_996253913.png",
    "original_poster_url": "https://akamaividz.zee5.com/resources/0-9-162/list/339x339/rbharat386x386_996253913.png"
  },
  {
    "live_tv_id": "30",
    "tv_name": "Zee News",
    "description": "",
    "slug": "",
    "stream_from": "hls",
    "stream_label": "HD",
    "user_agent": "ExoPlayerDemo/16.27.14 (Linux;Android 6.0.1) ExoPlayerLib/2.8.4",
    "stream_url": "https://angelon.top/apis/livetv/zee5/play.m3u8?id=ZEE_NEWS&token=ZnVja3lvdWJpdGNo",
    "thumbnail_url": "zeenews_883634939.png",
    "poster_url": "zeenews_883634939.png",
    "original_thumbnail_url": "https://akamaividz.zee5.com/resources/0-9-zeenews/list/339x339/zeenews_883634939.png",
    "original_poster_url": "https://akamaividz.zee5.com/resources/0-9-zeenews/list/339x339/zeenews_883634939.png"
  },
  {
    "live_tv_id": "31",
    "tv_name": "&xplorHD",
    "description": "",
    "slug": "",
    "stream_from": "hls",
    "stream_label": "HD",
    "user_agent": "ExoPlayerDemo/16.27.14 (Linux;Android 6.0.1) ExoPlayerLib/2.8.4",
    "stream_url": "https://angelon.top/apis/livetv/zee5/play.m3u8?id=&XPLORHD&token=ZnVja3lvdWJpdGNo",
    "thumbnail_url": "1170x658_1036205659.png",
    "poster_url": "1170x658_1036205659.png",
    "original_thumbnail_url": "https://akamaividz.zee5.com/resources/0-9-209/list/339x339/1170x658_1036205659.png",
    "original_poster_url": "https://akamaividz.zee5.com/resources/0-9-209/list/339x339/1170x658_1036205659.png"
  },
  {
    "live_tv_id": "32",
    "tv_name": "Zee Classic",
    "description": "",
    "slug": "",
    "stream_from": "hls",
    "stream_label": "HD",
    "user_agent": "ExoPlayerDemo/16.27.14 (Linux;Android 6.0.1) ExoPlayerLib/2.8.4",
    "stream_url": "https://angelon.top/apis/livetv/zee5/play.m3u8?id=ZEE_CLASSIC&token=ZnVja3lvdWJpdGNo",
    "thumbnail_url": "1170x658_1734999631.png",
    "poster_url": "1170x658_1734999631.png",
    "original_thumbnail_url": "https://akamaividz.zee5.com/resources/0-9-176/list/339x339/1170x658_1734999631.png",
    "original_poster_url": "https://akamaividz.zee5.com/resources/0-9-176/list/339x339/1170x658_1734999631.png"
  },
  {
    "live_tv_id": "33",
    "tv_name": "E24",
    "description": "",
    "slug": "",
    "stream_from": "hls",
    "stream_label": "HD",
    "user_agent": "ExoPlayerDemo/16.27.14 (Linux;Android 6.0.1) ExoPlayerLib/2.8.4",
    "stream_url": "https://angelon.top/apis/livetv/zee5/play.m3u8?id=E24&token=ZnVja3lvdWJpdGNo",
    "thumbnail_url": "1170x658_421011435.png",
    "poster_url": "1170x658_421011435.png",
    "original_thumbnail_url": "https://akamaividz.zee5.com/resources/0-9-207/list/339x339/1170x658_421011435.png",
    "original_poster_url": "https://akamaividz.zee5.com/resources/0-9-207/list/339x339/1170x658_421011435.png"
  },
  {
    "live_tv_id": "34",
    "tv_name": "The Q India HD",
    "description": "",
    "slug": "",
    "stream_from": "hls",
    "stream_label": "HD",
    "user_agent": "ExoPlayerDemo/16.27.14 (Linux;Android 6.0.1) ExoPlayerLib/2.8.4",
    "stream_url": "https://angelon.top/apis/livetv/zee5/play.m3u8?id=THE_Q_INDIA_HD&token=ZnVja3lvdWJpdGNo",
    "thumbnail_url": "qindia_1170x658.png",
    "poster_url": "qindia_1170x658.png",
    "original_thumbnail_url": "https://akamaividz.zee5.com/resources/0-9-181/list/339x339/qindia_1170x658.png",
    "original_poster_url": "https://akamaividz.zee5.com/resources/0-9-181/list/339x339/qindia_1170x658.png"
  },
  {
    "live_tv_id": "35",
    "tv_name": "Boogle Bollywood",
    "description": "",
    "slug": "",
    "stream_from": "hls",
    "stream_label": "HD",
    "user_agent": "ExoPlayerDemo/16.27.14 (Linux;Android 6.0.1) ExoPlayerLib/2.8.4",
    "stream_url": "https://angelon.top/apis/livetv/zee5/play.m3u8?id=BOOGLE_BOLLYWOOD&token=ZnVja3lvdWJpdGNo",
    "thumbnail_url": "booglebollywood386x386.png",
    "poster_url": "booglebollywood386x386.png",
    "original_thumbnail_url": "https://akamaividz.zee5.com/resources/0-9-165/list/339x339/booglebollywood386x386.png",
    "original_poster_url": "https://akamaividz.zee5.com/resources/0-9-165/list/339x339/booglebollywood386x386.png"
  },
  {
    "live_tv_id": "36",
    "tv_name": "&flix",
    "description": "",
    "slug": "",
    "stream_from": "hls",
    "stream_label": "HD",
    "user_agent": "ExoPlayerDemo/16.27.14 (Linux;Android 6.0.1) ExoPlayerLib/2.8.4",
    "stream_url": "https://angelon.top/apis/livetv/zee5/play.m3u8?id=&FLIX&token=ZnVja3lvdWJpdGNo",
    "thumbnail_url": "flixcolour_386x_2111987543.png",
    "poster_url": "flixcolour_386x_2111987543.png",
    "original_thumbnail_url": "https://akamaividz.zee5.com/resources/0-9-channel_2105335046/list/339x339/flixcolour_386x_2111987543.png",
    "original_poster_url": "https://akamaividz.zee5.com/resources/0-9-channel_2105335046/list/339x339/flixcolour_386x_2111987543.png"
  },
  {
    "live_tv_id": "37",
    "tv_name": "&Priv\u00e9 HD",
    "description": "",
    "slug": "",
    "stream_from": "hls",
    "stream_label": "HD",
    "user_agent": "ExoPlayerDemo/16.27.14 (Linux;Android 6.0.1) ExoPlayerLib/2.8.4",
    "stream_url": "https://angelon.top/apis/livetv/zee5/play.m3u8?id=&PRIV\u00e9_HD&token=ZnVja3lvdWJpdGNo",
    "thumbnail_url": "h2logo386x386_104752233.png",
    "poster_url": "h2logo386x386_104752233.png",
    "original_thumbnail_url": "https://akamaividz.zee5.com/resources/0-9-priv\u00e9hd/list/339x339/h2logo386x386_104752233.png",
    "original_poster_url": "https://akamaividz.zee5.com/resources/0-9-priv\u00e9hd/list/339x339/h2logo386x386_104752233.png"
  },
  {
    "live_tv_id": "38",
    "tv_name": "Zee Caf\u00e9 HD",
    "description": "",
    "slug": "",
    "stream_from": "hls",
    "stream_label": "HD",
    "user_agent": "ExoPlayerDemo/16.27.14 (Linux;Android 6.0.1) ExoPlayerLib/2.8.4",
    "stream_url": "https://angelon.top/apis/livetv/zee5/play.m3u8?id=ZEE_CAF\u00e9_HD&token=ZnVja3lvdWJpdGNo",
    "thumbnail_url": "zeecafehd_1363288667.png",
    "poster_url": "zeecafehd_1363288667.png",
    "original_thumbnail_url": "https://akamaividz.zee5.com/resources/0-9-zeecafehd/list/339x339/zeecafehd_1363288667.png",
    "original_poster_url": "https://akamaividz.zee5.com/resources/0-9-zeecafehd/list/339x339/zeecafehd_1363288667.png"
  }
]